pyserialization/__init__.py
pyserialization/composite.py
pyserialization/endianness.py
pyserialization/serialbytes.py
pyserialization/serialchar.py
pyserialization/serialenum.py
pyserialization/serialfloat.py
pyserialization/serialimage.py
pyserialization/serialint.py
pyserialization/serializable.py
pyserialization/seriallist.py
pyserialization/serialndarray.py
pyserialization/serialstring.py
pyserialization/union.py
PySerialization-1.2.dist-info/METADATA
PySerialization-1.2.dist-info/WHEEL
PySerialization-1.2.dist-info/license.txt
PySerialization-1.2.dist-info/top_level.txt
PySerialization-1.2.dist-info/RECORD
