Metadata-Version: 2.1
Name: PySerialization
Version: 1.2
Summary: Set of classes allowing easy serialization of simple and composite types
Home-page: https://github.com/vinceshores
Author: Vince Shores
Author-email: vince.shores@outlook.com
License: UNKNOWN
Platform: UNKNOWN
Classifier: Intended Audience :: Developers
Classifier: License :: OSI Approved :: MIT License
Classifier: Programming Language :: Python :: 3
Classifier: Topic :: Software Development
Requires-Python: >=3.4
Provides-Extra: saveableimage
Requires-Dist: PIL ; extra == 'saveableimage'
Provides-Extra: saveablendarray
Requires-Dist: numpy ; extra == 'saveablendarray'
